delft_fiat-0.3.2.dist-info/licenses/LICENSE
fiat/__init__.py
fiat/cfg.py
fiat/check.py
fiat/error.py
fiat/fio.py
fiat/log.py
fiat/util.py
fiat/version.py
fiat/cli/__init__.py
fiat/cli/action.py
fiat/cli/formatter.py
fiat/cli/main.py
fiat/cli/util.py
fiat/gis/__init__.py
fiat/gis/geom.py
fiat/gis/grid.py
fiat/gis/overlay.py
fiat/gis/util.py
fiat/methods/__init__.py
fiat/methods/ead.py
fiat/methods/flood.py
fiat/methods/util.py
fiat/models/__init__.py
fiat/models/base.py
fiat/models/geom.py
fiat/models/grid.py
fiat/models/util.py
fiat/models/worker_geom.py
fiat/models/worker_grid.py
delft_fiat-0.3.2.dist-info/METADATA
delft_fiat-0.3.2.dist-info/WHEEL
delft_fiat-0.3.2.dist-info/entry_points.txt
delft_fiat-0.3.2.dist-info/top_level.txt
delft_fiat-0.3.2.dist-info/RECORD
