Metadata-Version: 2.4
Name: delft_fiat
Version: 0.3.2
Summary: Delft Fast Impact Assessment Tool
Author-email: "B.W. Dalmijn" <brencodeert@outlook.com>, "F.C. de Groen" <frederique.degroen@deltares.nl>, "S.A. Rautenbach" <sarah.rautenbach@deltares.nl>, "P. Athanasiou" <panos.athanasiou@deltares.nl>
Maintainer-email: "B.W. Dalmijn" <brencodeert@outlook.com>
License: MIT
Project-URL: Homepage, https://deltares.github.io/Delft-FIAT/stable/
Project-URL: Bug Reports, https://github.com/Deltares/Delft-FIAT/issues
Project-URL: Source, https://github.com/Deltares/Delft-FIAT
Keywords: FIAT,Assessment,Damage
Classifier: Development Status :: 4 - Beta
Classifier: Intended Audience :: End Users/Desktop
Classifier: Intended Audience :: Developers
Classifier: Intended Audience :: Science/Research
Classifier: Topic :: Scientific/Engineering :: Hydrology
Classifier: Topic :: Scientific/Engineering :: GIS
Classifier: License :: OSI Approved :: MIT License
Classifier: Natural Language :: English
Classifier: Operating System :: OS Independent
Classifier: Programming Language :: Python :: 3
Classifier: Programming Language :: Python :: 3.11
Classifier: Programming Language :: Python :: 3.12
Classifier: Programming Language :: Python :: 3.13
Requires-Python: >=3.11
License-File: LICENSE
Requires-Dist: gdal>=3.5
Requires-Dist: numpy
Requires-Dist: regex
Provides-Extra: all
Requires-Dist: setuptools>=61.0.0; extra == "all"
Provides-Extra: build
Requires-Dist: pyinstaller>=6.0.0; extra == "build"
Requires-Dist: delft_fiat[all,extra]; extra == "build"
Provides-Extra: dev
Requires-Dist: cython; extra == "dev"
Requires-Dist: pre-commit; extra == "dev"
Requires-Dist: ruff; extra == "dev"
Requires-Dist: delft_fiat[all,docs,extra,test]; extra == "dev"
Provides-Extra: docs
Requires-Dist: jupyter; extra == "docs"
Requires-Dist: jupyter-cache; extra == "docs"
Requires-Dist: matplotlib; extra == "docs"
Requires-Dist: pandas; extra == "docs"
Requires-Dist: quartodoc>=0.7.6; extra == "docs"
Requires-Dist: delft_fiat[all,extra]; extra == "docs"
Provides-Extra: extra
Requires-Dist: tomli-w; extra == "extra"
Provides-Extra: test
Requires-Dist: pytest>=2.7.3; extra == "test"
Requires-Dist: pytest-cov; extra == "test"
Requires-Dist: pytest-mock; extra == "test"
Requires-Dist: responses; extra == "test"
Requires-Dist: delft_fiat[all,extra]; extra == "test"
Dynamic: license-file
